solidgate/__init__.py
solidgate/api_client.py
solidgate/encryption.py
solidgate/model.py
solidgate_card_sdk-0.1.0.dist-info/LICENSE.md
solidgate_card_sdk-0.1.0.dist-info/METADATA
solidgate_card_sdk-0.1.0.dist-info/WHEEL
solidgate_card_sdk-0.1.0.dist-info/top_level.txt
solidgate_card_sdk-0.1.0.dist-info/RECORD
