Metadata-Version: 2.1
Name: solidgate-card-sdk
Version: 0.1.0
Summary: Python API SDK for SolidGate payment gateway
Home-page: https://solidgate.atlassian.net/wiki/spaces/API/overview
Author: SolidGate
Author-email: info@solidgate.com
License: UNKNOWN
Platform: UNKNOWN
Classifier: Programming Language :: Python :: 3.7
Classifier: License :: OSI Approved :: MIT License
Classifier: Operating System :: OS Independent
License-File: LICENSE.md
Requires-Dist: requests
Requires-Dist: pycryptodome
